[{
    "img": "img/main_section01_01.jpg",
    "title": "고기 맛집 베스트 15곳",
    "desc": "\"무한고기 안녕\""
}, {
    "img": "img/main_section01_02.jpg",
    "title": "샐러드 맛집 베스트 7곳",
    "desc": "\"고기 더이상 못먹겠어\""
}, {
    "img": "img/main_section01_03.jpg",
    "title": "국수 맛집 베스트 6곳",
    "desc": "\"오늘은 면이 땡기는 날\""
}, {
    "img": "img/main_section01_04.jpg",
    "title": "아침식사 맛집 베스트 6곳",
    "desc": "\"아침 거르지 마세요~ ^^\""
}, {
    "img": "img/main_section01_01.jpg",
    "title": "고기 맛집 베스트 5곳",
    "desc": "\"무한고기 안녕\""
}, {
    "img": "img/main_section01_02.jpg",
    "title": "샐러드 맛집 베스트 7곳",
    "desc": "\"고기 더이상 못먹겠어\""
}, {
    "img": "img/main_section01_03.jpg",
    "title": "국수 맛집 베스트 6곳",
    "desc": "\"오늘은 면이 땡기는 날\""
}, {
    "img": "img/main_section01_04.jpg",
    "title": "아침식사 맛집 베스트 6곳",
    "desc": "\"아침 거르지 마세요~ ^^\""
}, {
    "img": "img/main_section01_01.jpg",
    "title": "고기 맛집 베스트 5곳",
    "desc": "\"무한고기 안녕\""
}, {
    "img": "img/main_section01_02.jpg",
    "title": "샐러드 맛집 베스트 7곳",
    "desc": "\"고기 더이상 못먹겠어\""
}, {
    "img": "img/main_section01_03.jpg",
    "title": "국수 맛집 베스트 6곳",
    "desc": "\"오늘은 면이 땡기는 날\""
}, {
    "img": "img/main_section01_04.jpg",
    "title": "아침식사 맛집 베스트 6곳",
    "desc": "\"아침 거르지 마세요~ ^^\""
}]
